{
  "windows": [
    {
      "train_start": "2025-11-01T00:00:00+00:00",
      "train_end": "2025-11-15T00:00:00+00:00",
      "test_start": "2025-11-15T00:00:00+00:00",
      "test_end": "2025-11-22T00:00:00+00:00",
      "trades": 0,
      "winrate": null,
      "gross_pnl": 0.0,
      "net_pnl": 0.0,
      "profit_factor": null,
      "max_dd": 0.0
    },
    {
      "train_start": "2025-11-08T00:00:00+00:00",
      "train_end": "2025-11-22T00:00:00+00:00",
      "test_start": "2025-11-22T00:00:00+00:00",
      "test_end": "2025-11-29T00:00:00+00:00",
      "trades": 0,
      "winrate": null,
      "gross_pnl": 0.0,
      "net_pnl": 0.0,
      "profit_factor": null,
      "max_dd": 0.0
    },
    {
      "train_start": "2025-11-15T00:00:00+00:00",
      "train_end": "2025-11-29T00:00:00+00:00",
      "test_start": "2025-11-29T00:00:00+00:00",
      "test_end": "2025-12-06T00:00:00+00:00",
      "trades": 0,
      "winrate": null,
      "gross_pnl": 0.0,
      "net_pnl": 0.0,
      "profit_factor": null,
      "max_dd": 0.0
    },
    {
      "train_start": "2025-11-22T00:00:00+00:00",
      "train_end": "2025-12-06T00:00:00+00:00",
      "test_start": "2025-12-06T00:00:00+00:00",
      "test_end": "2025-12-13T00:00:00+00:00",
      "trades": 232,
      "winrate": 0.3103448275862069,
      "gross_pnl": 9833.328571428472,
      "net_pnl": -15646.729245714385,
      "profit_factor": 0.36822618079287467,
      "max_dd": 0.015646729245713795
    },
    {
      "train_start": "2025-11-29T00:00:00+00:00",
      "train_end": "2025-12-13T00:00:00+00:00",
      "test_start": "2025-12-13T00:00:00+00:00",
      "test_end": "2025-12-20T00:00:00+00:00",
      "trades": 523,
      "winrate": 0.3365200764818356,
      "gross_pnl": 20728.84285714272,
      "net_pnl": -34470.18660428585,
      "profit_factor": 0.338178105888938,
      "max_dd": 0.035018105418466096
    },
    {
      "train_start": "2025-12-06T00:00:00+00:00",
      "train_end": "2025-12-20T00:00:00+00:00",
      "test_start": "2025-12-20T00:00:00+00:00",
      "test_end": "2025-12-27T00:00:00+00:00",
      "trades": 510,
      "winrate": 0.17254901960784313,
      "gross_pnl": 10771.964285714479,
      "net_pnl": -43128.33856142838,
      "profit_factor": 0.12707993288073033,
      "max_dd": 0.04540383893668464
    },
    {
      "train_start": "2025-12-13T00:00:00+00:00",
      "train_end": "2025-12-27T00:00:00+00:00",
      "test_start": "2025-12-27T00:00:00+00:00",
      "test_end": "2026-01-03T00:00:00+00:00",
      "trades": 399,
      "winrate": 0.09774436090225563,
      "gross_pnl": 727.4607142857712,
      "net_pnl": -41386.455806428516,
      "profit_factor": 0.04524021680365184,
      "max_dd": 0.04564239228719376
    }
  ],
  "summary": {
    "total_trades": 1664,
    "avg_trades_per_day": 33.95918367346939,
    "net_pnl": -134631.71021785715,
    "profit_factor": 0.20620251761133573,
    "max_dd": 0.13463171021785542,
    "worst_window": {
      "train_start": "2025-12-06T00:00:00+00:00",
      "train_end": "2025-12-20T00:00:00+00:00",
      "test_start": "2025-12-20T00:00:00+00:00",
      "test_end": "2025-12-27T00:00:00+00:00",
      "trades": 510,
      "winrate": 0.17254901960784313,
      "gross_pnl": 10771.964285714479,
      "net_pnl": -43128.33856142838,
      "profit_factor": 0.12707993288073033,
      "max_dd": 0.04540383893668464
    }
  }
}
